{"name":"Deathcore lvl.1","children":[{"class":"player","position":{"x":-608,"y":144,"z":0},"rotation":{"x":0,"y":0,"z":-17.271439482404848},"scale":{"x":16,"y":16,"z":16},"isStatic":false,"friction":0},{"class":"cube","position":{"x":0,"y":-64,"z":0},"rotation":{"x":0,"y":0,"z":0},"scale":{"x":128,"y":16,"z":16}},{"class":"cube","position":{"x":40,"y":-64,"z":0},"rotation":{"x":0,"y":0,"z":0},"scale":{"x":16,"y":16,"z":16}},{"class":"bounce","position":{"x":184,"y":-120,"z":0},"rotation":{"x":0,"y":0,"z":0},"scale":{"x":48,"y":16,"z":16}},{"class":"cube","position":{"x":432,"y":-112,"z":0},"rotation":{"x":0,"y":0,"z":0.7853981633974482},"scale":{"x":248,"y":16,"z":16}},{"class":"cube","position":{"x":288,"y":-72,"z":0},"rotation":{"x":0,"y":0,"z":0},"scale":{"x":16,"y":16,"z":16}},{"class":"spike","position":{"x":288,"y":-56,"z":0},"rotation":{"x":0,"y":0,"z":0},"scale":{"x":16,"y":16,"z":16}},{"class":"spike","position":{"x":288,"y":-88,"z":0},"rotation":{"x":0,"y":0,"z":-3.141592653589793},"scale":{"x":16,"y":16,"z":16}},{"class":"spike","position":{"x":304,"y":-72,"z":0},"rotation":{"x":0,"y":0,"z":-1.5707963267948963},"scale":{"x":16,"y":16,"z":16}},{"class":"spike","position":{"x":272,"y":-72,"z":0},"rotation":{"x":0,"y":0,"z":1.570796326794897},"scale":{"x":16,"y":16,"z":16}},{"class":"cube","position":{"x":240,"y":-264,"z":0},"rotation":{"x":0,"y":0,"z":0},"scale":{"x":128,"y":16,"z":16}},{"class":"direction","position":{"x":184,"y":-248,"z":0},"rotation":{"x":0,"y":0,"z":0},"scale":{"x":16,"y":16,"z":16}},{"class":"cube","position":{"x":368,"y":-312,"z":0},"rotation":{"x":0,"y":0,"z":0},"scale":{"x":48,"y":16,"z":16}},{"class":"cube","position":{"x":528,"y":-256,"z":0},"rotation":{"x":0,"y":0,"z":0},"scale":{"x":40,"y":16,"z":16}},{"class":"spike","position":{"x":496,"y":-256,"z":0},"rotation":{"x":0,"y":0,"z":1.5707963267948963},"scale":{"x":16,"y":16,"z":16}},{"class":"cube","position":{"x":552,"y":-256,"z":0},"rotation":{"x":0,"y":0,"z":0},"scale":{"x":16,"y":16,"z":16}},{"class":"checkpoint","position":{"x":200,"y":-248,"z":0},"rotation":{"x":0,"y":0,"z":0},"scale":{"x":16,"y":16,"z":16}},{"class":"cube","position":{"x":600,"y":-208,"z":0},"rotation":{"x":0,"y":0,"z":0},"scale":{"x":16,"y":16,"z":16}},{"class":"cube","position":{"x":584,"y":-256,"z":0},"rotation":{"x":0,"y":0,"z":0},"scale":{"x":16,"y":16,"z":16}},{"class":"cube","position":{"x":616,"y":-208,"z":0},"rotation":{"x":0,"y":0,"z":0},"scale":{"x":16,"y":16,"z":16}},{"class":"cube","position":{"x":600,"y":-256,"z":0},"rotation":{"x":0,"y":0,"z":0},"scale":{"x":16,"y":16,"z":16}},{"class":"cube","position":{"x":648,"y":-208,"z":0},"rotation":{"x":0,"y":0,"z":0},"scale":{"x":16,"y":16,"z":16}},{"class":"cube","position":{"x":632,"y":-256,"z":0},"rotation":{"x":0,"y":0,"z":0},"scale":{"x":16,"y":16,"z":16}},{"class":"cube","position":{"x":632,"y":-208,"z":0},"rotation":{"x":0,"y":0,"z":0},"scale":{"x":16,"y":16,"z":16}},{"class":"cube","position":{"x":616,"y":-256,"z":0},"rotation":{"x":0,"y":0,"z":0},"scale":{"x":16,"y":16,"z":16}},{"class":"cube","position":{"x":648,"y":-256,"z":0},"rotation":{"x":0,"y":0,"z":0},"scale":{"x":16,"y":16,"z":16}},{"class":"direction","position":{"x":696,"y":-168,"z":0},"rotation":{"x":0,"y":0,"z":3.141592653589793},"scale":{"x":16,"y":48,"z":16}},{"class":"cube","position":{"x":576,"y":-208,"z":0},"rotation":{"x":0,"y":0,"z":0},"scale":{"x":32,"y":16,"z":16}},{"class":"cube","position":{"x":568,"y":-256,"z":0},"rotation":{"x":0,"y":0,"z":0},"scale":{"x":16,"y":16,"z":16}},{"class":"cube","position":{"x":568,"y":-184,"z":0},"rotation":{"x":0,"y":0,"z":0},"scale":{"x":16,"y":32,"z":16}},{"class":"cube","position":{"x":-368,"y":0,"z":0},"rotation":{"x":0,"y":0,"z":0},"scale":{"x":392,"y":16,"z":16}},{"class":"spike","position":{"x":-432,"y":104,"z":0},"rotation":{"x":0,"y":0,"z":-3.141592653589793},"scale":{"x":16,"y":16,"z":16}},{"class":"cube","position":{"x":-432,"y":120,"z":0},"rotation":{"x":0,"y":0,"z":0},"scale":{"x":16,"y":16,"z":16}},{"class":"cube","position":{"x":-608,"y":48,"z":0},"rotation":{"x":0,"y":0,"z":-0.7853981633974484},"scale":{"x":112,"y":16,"z":16}},{"class":"spike","position":{"x":-448,"y":120,"z":0},"rotation":{"x":0,"y":0,"z":1.570796326794897},"scale":{"x":16,"y":16,"z":16}},{"class":"spike","position":{"x":-440,"y":16,"z":0},"rotation":{"x":0,"y":0,"z":0},"scale":{"x":16,"y":16,"z":16}},{"class":"cube","position":{"x":-120,"y":-32,"z":0},"rotation":{"x":0,"y":0,"z":-0.523598775598299},"scale":{"x":128,"y":16,"z":16}},{"class":"cube","position":{"x":184,"y":-232,"z":0},"rotation":{"x":0,"y":0,"z":0},"scale":{"x":16,"y":16,"z":16}},{"class":"cube","position":{"x":184,"y":-232,"z":0},"rotation":{"x":0,"y":0,"z":0},"scale":{"x":16,"y":16,"z":16}},{"class":"cube","position":{"x":552,"y":-176,"z":0},"rotation":{"x":0,"y":0,"z":0},"scale":{"x":16,"y":16,"z":16}},{"class":"cube","position":{"x":536,"y":-176,"z":0},"rotation":{"x":0,"y":0,"z":0},"scale":{"x":16,"y":16,"z":16}},{"class":"cube","position":{"x":696,"y":-256,"z":0},"rotation":{"x":0,"y":0,"z":0},"scale":{"x":16,"y":16,"z":16}},{"class":"cube","position":{"x":696,"y":-256,"z":0},"rotation":{"x":0,"y":0,"z":0},"scale":{"x":16,"y":16,"z":16}},{"class":"cube","position":{"x":696,"y":-240,"z":0},"rotation":{"x":0,"y":0,"z":0},"scale":{"x":16,"y":16,"z":16}},{"class":"cube","position":{"x":696,"y":-224,"z":0},"rotation":{"x":0,"y":0,"z":0},"scale":{"x":16,"y":16,"z":16}},{"class":"cube","position":{"x":696,"y":-208,"z":0},"rotation":{"x":0,"y":0,"z":0},"scale":{"x":16,"y":16,"z":16}},{"class":"spike","position":{"x":464,"y":-176,"z":0},"rotation":{"x":0,"y":0,"z":0},"scale":{"x":16,"y":16,"z":16}},{"class":"spike","position":{"x":480,"y":-176,"z":0},"rotation":{"x":0,"y":0,"z":0},"scale":{"x":16,"y":16,"z":16}},{"class":"spike","position":{"x":496,"y":-176,"z":0},"rotation":{"x":0,"y":0,"z":0},"scale":{"x":16,"y":16,"z":16}},{"class":"spike","position":{"x":512,"y":-176,"z":0},"rotation":{"x":0,"y":0,"z":0},"scale":{"x":16,"y":16,"z":16}},{"class":"spike","position":{"x":448,"y":-176,"z":0},"rotation":{"x":0,"y":0,"z":0},"scale":{"x":16,"y":16,"z":16}},{"class":"cube","position":{"x":672,"y":-256,"z":0},"rotation":{"x":0,"y":0,"z":1.5707963267948963},"scale":{"x":16,"y":24,"z":16}},{"class":"cube","position":{"x":528,"y":-472,"z":0},"rotation":{"x":0,"y":0,"z":0},"scale":{"x":96,"y":16,"z":16}},{"class":"cube","position":{"x":472,"y":-456,"z":0},"rotation":{"x":0,"y":0,"z":0},"scale":{"x":16,"y":16,"z":16}},{"class":"cube","position":{"x":472,"y":-456,"z":0},"rotation":{"x":0,"y":0,"z":0},"scale":{"x":16,"y":16,"z":16}},{"class":"cube","position":{"x":816,"y":-472,"z":0},"rotation":{"x":0,"y":0,"z":0},"scale":{"x":88,"y":16,"z":16}},{"class":"cube","position":{"x":704,"y":-432,"z":0},"rotation":{"x":0,"y":0,"z":0},"scale":{"x":48,"y":16,"z":16}},{"class":"spike","position":{"x":688,"y":-416,"z":0},"rotation":{"x":0,"y":0,"z":0},"scale":{"x":16,"y":16,"z":16}},{"class":"spike","position":{"x":720,"y":-416,"z":0},"rotation":{"x":0,"y":0,"z":0},"scale":{"x":16,"y":16,"z":16}},{"class":"spike","position":{"x":704,"y":-416,"z":0},"rotation":{"x":0,"y":0,"z":0},"scale":{"x":16,"y":16,"z":16}},{"class":"cube","position":{"x":1000,"y":-448,"z":0},"rotation":{"x":0,"y":0,"z":0},"scale":{"x":256,"y":16,"z":16}},{"class":"spike","position":{"x":864,"y":-448,"z":0},"rotation":{"x":0,"y":0,"z":1.5707963267948963},"scale":{"x":16,"y":16,"z":16}},{"class":"cube","position":{"x":1240,"y":-424,"z":0},"rotation":{"x":0,"y":0,"z":0},"scale":{"x":216,"y":16,"z":16}},{"class":"spike","position":{"x":1128,"y":-432,"z":0},"rotation":{"x":0,"y":0,"z":1.5707963267948963},"scale":{"x":16,"y":16,"z":16}},{"class":"cube","position":{"x":1472,"y":-528,"z":0},"rotation":{"x":0,"y":0,"z":0},"scale":{"x":88,"y":16,"z":16}},{"class":"spike","position":{"x":1160,"y":-408,"z":0},"rotation":{"x":0,"y":0,"z":0},"scale":{"x":16,"y":16,"z":16}},{"class":"spike","position":{"x":1144,"y":-408,"z":0},"rotation":{"x":0,"y":0,"z":0},"scale":{"x":16,"y":16,"z":16}},{"class":"direction","position":{"x":1512,"y":-504,"z":0},"rotation":{"x":0,"y":0,"z":3.141592653589793},"scale":{"x":16,"y":16,"z":16}},{"class":"cube","position":{"x":1304,"y":-504,"z":0},"rotation":{"x":0,"y":0,"z":0},"scale":{"x":144,"y":16,"z":16}},{"class":"cube","position":{"x":856,"y":-688,"z":0},"rotation":{"x":0,"y":0,"z":0},"scale":{"x":200,"y":16,"z":16}},{"class":"cube","position":{"x":1104,"y":-600,"z":0},"rotation":{"x":0,"y":0,"z":0},"scale":{"x":144,"y":16,"z":16}},{"class":"spike","position":{"x":944,"y":-672,"z":0},"rotation":{"x":0,"y":0,"z":0},"scale":{"x":16,"y":16,"z":16}},{"class":"spike","position":{"x":928,"y":-672,"z":0},"rotation":{"x":0,"y":0,"z":0},"scale":{"x":16,"y":16,"z":16}},{"class":"cube","position":{"x":528,"y":-688,"z":0},"rotation":{"x":0,"y":0,"z":0},"scale":{"x":200,"y":16,"z":16}},{"class":"spike","position":{"x":440,"y":-672,"z":0},"rotation":{"x":0,"y":0,"z":0},"scale":{"x":16,"y":16,"z":16}},{"class":"spike","position":{"x":456,"y":-672,"z":0},"rotation":{"x":0,"y":0,"z":0},"scale":{"x":16,"y":16,"z":16}},{"class":"spike","position":{"x":472,"y":-672,"z":0},"rotation":{"x":0,"y":0,"z":0},"scale":{"x":16,"y":16,"z":16}},{"class":"cube","position":{"x":32,"y":-624,"z":0},"rotation":{"x":0,"y":0,"z":0},"scale":{"x":200,"y":16,"z":16}},{"class":"cube","position":{"x":280,"y":-696,"z":0},"rotation":{"x":0,"y":0,"z":0},"scale":{"x":200,"y":16,"z":16}},{"class":"cube","position":{"x":-472,"y":-528,"z":0},"rotation":{"x":0,"y":0,"z":0},"scale":{"x":200,"y":16,"z":16}},{"class":"spike","position":{"x":-288,"y":-544,"z":0},"rotation":{"x":0,"y":0,"z":-1.5707963267948963},"scale":{"x":16,"y":16,"z":16}},{"class":"spike","position":{"x":-304,"y":-544,"z":0},"rotation":{"x":0,"y":0,"z":0},"scale":{"x":16,"y":16,"z":16}},{"class":"cube","position":{"x":-600,"y":-488,"z":0},"rotation":{"x":0,"y":0,"z":0},"scale":{"x":56,"y":64,"z":16}},{"class":"cube","position":{"x":-624,"y":-432,"z":0},"rotation":{"x":0,"y":0,"z":0},"scale":{"x":16,"y":16,"z":16}},{"class":"cube","position":{"x":-624,"y":-416,"z":0},"rotation":{"x":0,"y":0,"z":0},"scale":{"x":16,"y":16,"z":16}},{"class":"cube","position":{"x":-624,"y":-400,"z":0},"rotation":{"x":0,"y":0,"z":0},"scale":{"x":16,"y":16,"z":16}},{"class":"cube","position":{"x":-496,"y":-432,"z":0},"rotation":{"x":0,"y":0,"z":0},"scale":{"x":56,"y":64,"z":16}},{"class":"checkpoint","position":{"x":-200,"y":-544,"z":0},"rotation":{"x":0,"y":0,"z":0},"scale":{"x":16,"y":16,"z":16}},{"class":"direction","position":{"x":-624,"y":-448,"z":0},"rotation":{"x":0,"y":0,"z":0},"scale":{"x":16,"y":16,"z":16}},{"class":"cube","position":{"x":-472,"y":-376,"z":0},"rotation":{"x":0,"y":0,"z":0},"scale":{"x":16,"y":16,"z":16}},{"class":"cube","position":{"x":-472,"y":-360,"z":0},"rotation":{"x":0,"y":0,"z":0},"scale":{"x":16,"y":16,"z":16}},{"class":"direction","position":{"x":-472,"y":-392,"z":0},"rotation":{"x":0,"y":0,"z":3.141592653589793},"scale":{"x":16,"y":16,"z":16}},{"class":"cube","position":{"x":-616,"y":-368,"z":0},"rotation":{"x":0,"y":0,"z":0},"scale":{"x":56,"y":64,"z":16}},{"class":"spike","position":{"x":-792,"y":-392,"z":0},"rotation":{"x":0,"y":0,"z":0},"scale":{"x":16,"y":16,"z":16}},{"class":"spike","position":{"x":-776,"y":-392,"z":0},"rotation":{"x":0,"y":0,"z":0},"scale":{"x":16,"y":16,"z":16}},{"class":"spike","position":{"x":-760,"y":-392,"z":0},"rotation":{"x":0,"y":0,"z":0},"scale":{"x":16,"y":16,"z":16}},{"class":"spike","position":{"x":-744,"y":-392,"z":0},"rotation":{"x":0,"y":0,"z":0},"scale":{"x":16,"y":16,"z":16}},{"class":"spike","position":{"x":-728,"y":-392,"z":0},"rotation":{"x":0,"y":0,"z":0},"scale":{"x":16,"y":16,"z":16}},{"class":"spike","position":{"x":-712,"y":-392,"z":0},"rotation":{"x":0,"y":0,"z":0},"scale":{"x":16,"y":16,"z":16}},{"class":"spike","position":{"x":-696,"y":-392,"z":0},"rotation":{"x":0,"y":0,"z":0},"scale":{"x":16,"y":16,"z":16}},{"class":"spike","position":{"x":-688,"y":-392,"z":0},"rotation":{"x":0,"y":0,"z":0},"scale":{"x":16,"y":16,"z":16}},{"class":"cube","position":{"x":-672,"y":-272,"z":0},"rotation":{"x":0,"y":0,"z":0},"scale":{"x":16,"y":88,"z":16}},{"class":"spike","position":{"x":-672,"y":-392,"z":0},"rotation":{"x":0,"y":0,"z":0},"scale":{"x":16,"y":16,"z":16}},{"class":"finish","position":{"x":-664,"y":-528,"z":0},"rotation":{"x":0,"y":0,"z":0},"scale":{"x":152,"y":16,"z":16}},{"class":"direction","position":{"x":-216,"y":-560,"z":0},"rotation":{"x":0,"y":0,"z":3.141592653589793},"scale":{"x":200,"y":16,"z":16}},{"class":"tip","position":{"x":528,"y":-136,"z":0},"rotation":{"x":0,"y":0,"z":5.551115123125783e-17},"scale":{"x":16,"y":32,"z":16},"text":"Oops, you are on the wrong way! fall on the spikes to respawn and think. *HINT: UPS AND DOWNS WE ALL FALL FOR THE CROWN*"},{"class":"tip","position":{"x":-432,"y":72,"z":0},"rotation":{"x":0,"y":0,"z":0},"scale":{"x":16,"y":32,"z":16},"text":"Beat the record of 25.5 secs!"},{"class":"tip","position":{"x":-648,"y":-496,"z":0},"rotation":{"x":0,"y":0,"z":0},"scale":{"x":40,"y":16,"z":16},"text":"Like for part 2"}]}